yartsu/__init__.py
yartsu/_export_format.py
yartsu/_run_cmd.py
yartsu/_version.py
yartsu/argparse.py
yartsu/cli.py
yartsu/console.py
yartsu/term.py
yartsu/themes.py
yartsu-23.5.1b1.dist-info/entry_points.txt
yartsu-23.5.1b1.dist-info/WHEEL
yartsu-23.5.1b1.dist-info/METADATA
yartsu-23.5.1b1.dist-info/licenses/LICENSE.txt
yartsu-23.5.1b1.dist-info/RECORD
