Metadata-Version: 2.1
Name: yartsu
Version: 23.5.1b1
Summary: yartsu, another rich terminal screenshot utility
License: MIT
Author-email: Daylin Morgan <daylinmorgan@gmail.com>
Requires-Python: >=3.7
Requires-Dist: importlib-metadata>=4.11.4; python_version < "3.8"
Requires-Dist: rich>=13.3.5
Project-URL: Homepage, https://github.com/daylinmorgan/yartsu
Project-URL: Repository, https://github.com/daylinmorgan/yartsu
